README.rst
setup.py
anybox/__init__.py
anybox.nose.odoo.egg-info/PKG-INFO
anybox.nose.odoo.egg-info/SOURCES.txt
anybox.nose.odoo.egg-info/dependency_links.txt
anybox.nose.odoo.egg-info/entry_points.txt
anybox.nose.odoo.egg-info/namespace_packages.txt
anybox.nose.odoo.egg-info/not-zip-safe
anybox.nose.odoo.egg-info/requires.txt
anybox.nose.odoo.egg-info/top_level.txt
anybox/nose/__init__.py
anybox/nose/odoo/__init__.py