Metadata-Version: 1.1
Name: anybox.nose.odoo
Version: 0.1
Summary: Console script to run nose with the good import
Home-page: https://bitbucket.org/anybox/anybox.nose.odoo
Author: Jean-Sebastien Suzanne
Author-email: jssuzanne@anybox.fr
License: GPLv3
Platform: UNKNOWN
Classifier: License :: OSI Approved :: GNU General Public License v3 or later (GPLv3+)
Classifier: Topic :: Software Development :: Quality Assurance
Classifier: Topic :: Software Development :: Testing
Classifier: Topic :: System :: Benchmark
